LICENSE
README.md
pyproject.toml
setup.cfg
setup.py
./canvasxpress/__init__.py
./canvasxpress/canvas.py
./canvasxpress/plot.py
./canvasxpress/config/__init__.py
./canvasxpress/config/collection.py
./canvasxpress/config/type.py
./canvasxpress/data/__init__.py
./canvasxpress/data/base.py
./canvasxpress/data/convert.py
./canvasxpress/data/keypair.py
./canvasxpress/data/matrix.py
./canvasxpress/data/text.py
./canvasxpress/data/url.py
./canvasxpress/js/__init__.py
./canvasxpress/js/collection.py
./canvasxpress/js/function.py
./canvasxpress/render/__init__.py
./canvasxpress/render/base.py
./canvasxpress/render/dash.py
./canvasxpress/render/environment.py
./canvasxpress/render/image.py
./canvasxpress/render/json.py
./canvasxpress/render/jupyter.py
./canvasxpress/render/popup.py
./canvasxpress/render/rstudio.py
./canvasxpress/render/shiny.py
./canvasxpress/render/streamlit.py
./canvasxpress/util/__init__.py
./canvasxpress/util/template.py
./canvasxpress/util/example/__init__.py
./canvasxpress/util/example/generate_tutorials.py
./canvasxpress/util/example/generator.py
./cxdash/CXDashElement.py
./cxdash/__init__.py
./cxdash/_imports_.py
./cxdash/cxdash.min.js
./cxdash/cxdash.min.js.LICENSE.txt
./cxdash/metadata.json
./cxdash/package-info.json
./tutorials/console/__init__.py
./tutorials/console/heatmap_7.py
./tutorials/console/scatter2d_12.py
./tutorials/dash/__init__.py
./tutorials/dash/mixed_canvasxpress_plotly_example.py
./tutorials/dash/mixed_canvasxpress_plotly_example2.py
./tutorials/dash/mixed_cxdashelement_plotly_example.py
./tutorials/dash/simple_canvasxpress_example.py
./tutorials/dash/simple_cxdashelement_example.py
canvasxpress.egg-info/PKG-INFO
canvasxpress.egg-info/SOURCES.txt
canvasxpress.egg-info/dependency_links.txt
canvasxpress.egg-info/requires.txt
canvasxpress.egg-info/top_level.txt