Metadata-Version: 2.4
Name: canvasxpress
Version: 2026.1.25.2108
Summary: CanvasXpress for Python
Home-page: https://github.com/docinfosci/canvasxpress-python.git
Author:  Dr. Isaac Neuhaus for CanvasXpress JS, PHP, and R; Dr. Constance M. Brett for R; Dr. Todd C. Brett for Python and Dash; and Dr. Jennifer Walker for Python.
Author-email: todd@aggregate-genius.com
License: Copyright 2020 to 2026 CanvasXpress all rights reserved
Project-URL: Documentation, https://canvasxpress-python.readthedocs.io
Classifier: Development Status :: 5 - Production/Stable
Classifier: Intended Audience :: Developers
Classifier: Intended Audience :: Science/Research
Classifier: Environment :: Web Environment
Classifier: Topic :: Multimedia :: Graphics
Classifier: Topic :: Scientific/Engineering :: Information Analysis
Classifier: License :: OSI Approved :: MIT License
Classifier: Programming Language :: Python :: 3
Classifier: Programming Language :: Python :: 3
Requires-Python: >=3.6
License-File: LICENSE
Requires-Dist: deepdiff
Requires-Dist: gitpython>=3
Requires-Dist: pytz>=2020.1
Requires-Dist: pandas>=1.1.5
Requires-Dist: requests>=2
Requires-Dist: Deprecated>=1.2.12
Provides-Extra: core
Requires-Dist: deepdiff; extra == "core"
Requires-Dist: gitpython>=3; extra == "core"
Requires-Dist: pytz>=2020.1; extra == "core"
Requires-Dist: pandas>=1.1.5; extra == "core"
Requires-Dist: requests>=2; extra == "core"
Requires-Dist: Deprecated>=1.2.12; extra == "core"
Provides-Extra: dash
Requires-Dist: deepdiff; extra == "dash"
Requires-Dist: gitpython>=3; extra == "dash"
Requires-Dist: pytz>=2020.1; extra == "dash"
Requires-Dist: pandas>=1.1.5; extra == "dash"
Requires-Dist: requests>=2; extra == "dash"
Requires-Dist: Deprecated>=1.2.12; extra == "dash"
Requires-Dist: dash; extra == "dash"
Provides-Extra: streamlit
Requires-Dist: deepdiff; extra == "streamlit"
Requires-Dist: gitpython>=3; extra == "streamlit"
Requires-Dist: pytz>=2020.1; extra == "streamlit"
Requires-Dist: pandas>=1.1.5; extra == "streamlit"
Requires-Dist: requests>=2; extra == "streamlit"
Requires-Dist: Deprecated>=1.2.12; extra == "streamlit"
Requires-Dist: streamlit; extra == "streamlit"
Provides-Extra: jupyter
Requires-Dist: deepdiff; extra == "jupyter"
Requires-Dist: gitpython>=3; extra == "jupyter"
Requires-Dist: pytz>=2020.1; extra == "jupyter"
Requires-Dist: pandas>=1.1.5; extra == "jupyter"
Requires-Dist: requests>=2; extra == "jupyter"
Requires-Dist: Deprecated>=1.2.12; extra == "jupyter"
Requires-Dist: jupyter; extra == "jupyter"
Requires-Dist: IPython>=7; extra == "jupyter"
Requires-Dist: beautifulsoup4>=4; extra == "jupyter"
Requires-Dist: htmlmin>=0.1.12; extra == "jupyter"
Requires-Dist: requests; extra == "jupyter"
Provides-Extra: shiny
Requires-Dist: deepdiff; extra == "shiny"
Requires-Dist: gitpython>=3; extra == "shiny"
Requires-Dist: pytz>=2020.1; extra == "shiny"
Requires-Dist: pandas>=1.1.5; extra == "shiny"
Requires-Dist: requests>=2; extra == "shiny"
Requires-Dist: Deprecated>=1.2.12; extra == "shiny"
Requires-Dist: shiny; extra == "shiny"
Requires-Dist: htmltools; extra == "shiny"
Requires-Dist: ipywidgets; extra == "shiny"
Requires-Dist: shinywidgets; extra == "shiny"
Provides-Extra: rstudio
Requires-Dist: deepdiff; extra == "rstudio"
Requires-Dist: gitpython>=3; extra == "rstudio"
Requires-Dist: pytz>=2020.1; extra == "rstudio"
Requires-Dist: pandas>=1.1.5; extra == "rstudio"
Requires-Dist: requests>=2; extra == "rstudio"
Requires-Dist: Deprecated>=1.2.12; extra == "rstudio"
Requires-Dist: shiny; extra == "rstudio"
Requires-Dist: htmltools; extra == "rstudio"
Requires-Dist: ipywidgets; extra == "rstudio"
Requires-Dist: shinywidgets; extra == "rstudio"
Requires-Dist: jupyter; extra == "rstudio"
Requires-Dist: IPython>=7; extra == "rstudio"
Requires-Dist: beautifulsoup4>=4; extra == "rstudio"
Requires-Dist: htmlmin>=0.1.12; extra == "rstudio"
Requires-Dist: requests; extra == "rstudio"
Requires-Dist: rpy2; extra == "rstudio"
Provides-Extra: all
Requires-Dist: deepdiff; extra == "all"
Requires-Dist: gitpython>=3; extra == "all"
Requires-Dist: pytz>=2020.1; extra == "all"
Requires-Dist: pandas>=1.1.5; extra == "all"
Requires-Dist: requests>=2; extra == "all"
Requires-Dist: Deprecated>=1.2.12; extra == "all"
Requires-Dist: dash; extra == "all"
Requires-Dist: jupyter; extra == "all"
Requires-Dist: IPython>=7; extra == "all"
Requires-Dist: beautifulsoup4>=4; extra == "all"
Requires-Dist: htmlmin>=0.1.12; extra == "all"
Requires-Dist: requests; extra == "all"
Dynamic: author
Dynamic: author-email
Dynamic: classifier
Dynamic: description
Dynamic: description-content-type
Dynamic: home-page
Dynamic: license
Dynamic: license-file
Dynamic: project-url
Dynamic: provides-extra
Dynamic: requires-dist
Dynamic: requires-python
Dynamic: summary
